kivymd_extensions/__init__.py
kivymd_extensions/akivymd/__init__.py
kivymd_extensions/akivymd/factory_registers.py
kivymd_extensions/akivymd/helper.py
kivymd_extensions/akivymd/uix/__init__.py
kivymd_extensions/akivymd/uix/badgelayout.py
kivymd_extensions/akivymd/uix/bottomappbar.py
kivymd_extensions/akivymd/uix/bottomnavigation.py
kivymd_extensions/akivymd/uix/bottomnavigation2.py
kivymd_extensions/akivymd/uix/buttonpanel.py
kivymd_extensions/akivymd/uix/cardstack.py
kivymd_extensions/akivymd/uix/charts.py
kivymd_extensions/akivymd/uix/datepicker.py
kivymd_extensions/akivymd/uix/dialogs.py
kivymd_extensions/akivymd/uix/hintwidget.py
kivymd_extensions/akivymd/uix/imageview.py
kivymd_extensions/akivymd/uix/loaders.py
kivymd_extensions/akivymd/uix/navigationrail.py
kivymd_extensions/akivymd/uix/onboarding.py
kivymd_extensions/akivymd/uix/progressbutton.py
kivymd_extensions/akivymd/uix/progresswidget.py
kivymd_extensions/akivymd/uix/rating.py
kivymd_extensions/akivymd/uix/selectionlist.py
kivymd_extensions/akivymd/uix/silverappbar.py
kivymd_extensions/akivymd/uix/spinners.py
kivymd_extensions/akivymd/uix/statusbarcolor.py
kivymd_extensions/akivymd/uix/swipemenu.py
kivymd_extensions/akivymd/uix/toolbar.py
kivymd_extensions/akivymd/uix/windows.py
kivymd_extensions/akivymd/uix/behaviors/__init__.py
kivymd_extensions/akivymd/uix/behaviors/addwidget.py
kivymd_extensions/akivymd/uix/behaviors/labelanimation.py
kivymd_extensions/akivymd/utils/__init__.py
kivymd_extensions/akivymd/utils/draw_tools.py
kivymd_extensions.akivymd-1.2.7.dist-info/LICENSE
kivymd_extensions.akivymd-1.2.7.dist-info/METADATA
kivymd_extensions.akivymd-1.2.7.dist-info/WHEEL
kivymd_extensions.akivymd-1.2.7.dist-info/top_level.txt
kivymd_extensions.akivymd-1.2.7.dist-info/RECORD
